jackselect/__init__.py
jackselect/__main__.py
jackselect/a2jcontrol.py
jackselect/alsainfo.py
jackselect/dbusinterface.py
jackselect/devmonitor.py
jackselect/indicator.py
jackselect/jackcontrol.py
jackselect/jackselect.py
jackselect/jackselect_service.py
jackselect/pyudev_gobject.py
jackselect/qjackctlconf.py
jackselect/version.py
jackselect/images/jack.png
jackselect/images/midi.png
jackselect/images/quit.png
jackselect/images/start.png
jackselect/images/started.png
jackselect/images/stop.png
jackselect/images/stopped.png
jack_select-1.5.2.dist-info/LICENSE
jack_select-1.5.2.dist-info/METADATA
jack_select-1.5.2.dist-info/WHEEL
jack_select-1.5.2.dist-info/entry_points.txt
jack_select-1.5.2.dist-info/top_level.txt
jack_select-1.5.2.dist-info/RECORD
