Metadata-Version: 2.1
Name: jack-select
Version: 1.5.2
Summary: A systray app to set the JACK configuration from QjackCtl presets via DBus.
Home-page: https://github.com/SpotlightKid/jack-select
Author: Christopher Arndt
Author-email: chris@chrisarndt.de
License: UNKNOWN
Keywords: JACK,systray,GTK,DBus,audio
Platform: UNKNOWN
Classifier: Development Status :: 5 - Production/Stable
Classifier: Intended Audience :: End Users/Desktop
Classifier: License :: OSI Approved :: MIT License
Classifier: Operating System :: POSIX
Classifier: Programming Language :: Python
Classifier: Programming Language :: Python :: 3
Classifier: Programming Language :: Python :: 3.6
Classifier: Programming Language :: Python :: 3.7
Classifier: Programming Language :: Python :: 3.8
Classifier: Programming Language :: Python :: 3.9
Classifier: Programming Language :: Python :: 3.10
Classifier: Environment :: X11 Applications :: GTK
Classifier: Topic :: Multimedia :: Sound/Audio
License-File: LICENSE
Requires-Dist: PyGObject
Requires-Dist: dbus-python
Requires-Dist: pyudev
Requires-Dist: pyxdg
